generative_diffusion/__init__.py
generative_diffusion/controllable/__init__.py
generative_diffusion/controllable/base_controller.py
generative_diffusion/controllable/imputation_controller.py
generative_diffusion/controllable/imputation_mask_functions.py
generative_diffusion/diffusion/__init__.py
generative_diffusion/diffusion/diffusion_core.py
generative_diffusion/diffusion/diffusion_factory.py
generative_diffusion/diffusion/losses.py
generative_diffusion/diffusion/utils.py
generative_diffusion/measures/__init__.py
generative_diffusion/measures/measures.py
generative_diffusion/samplers/__init__.py
generative_diffusion/samplers/base_sampler.py
generative_diffusion/samplers/euler_maruyama.py
generative_diffusion/samplers/exponential_integrator.py
generative_diffusion/samplers/predictor_corrector.py
generative_diffusion/samplers/probability_flow_ode.py
generative_diffusion/schedulers/__init__.py
generative_diffusion/schedulers/base_scheduler.py
generative_diffusion/schedulers/constant_scheduler.py
generative_diffusion/schedulers/cosine_scheduler.py
generative_diffusion/schedulers/linear_scheduler.py
generative_diffusion/score_networks/__init__.py
generative_diffusion/score_networks/base_score_model.py
generative_diffusion/score_networks/unet_score_network.py
generative_diffusion/sde/__init__.py
generative_diffusion/sde/base_sde.py
generative_diffusion/sde/scheduler_sde.py
generative_diffusion/sde/subvp_sde.py
generative_diffusion/sde/ve_sde.py
generative_diffusion/sde/vp_sde.py
generative_diffusion/utils/__init__.py
generative_diffusion/utils/data_utils.py
generative_diffusion/utils/visualization_utils.py
generative_diffusion-0.1.3.dist-info/licenses/LICENSE
generative_diffusion-0.1.3.dist-info/METADATA
generative_diffusion-0.1.3.dist-info/WHEEL
generative_diffusion-0.1.3.dist-info/top_level.txt
generative_diffusion-0.1.3.dist-info/RECORD
