Metadata-Version: 2.4
Name: generative-diffusion
Version: 0.1.3
Summary: Toolkit modular en Python para modelos generativos basados en difusión
Author-email: Manuel Muñoz <manuel.munnozb@estudiante.uam.es>, Daniel Ortiz <daniel.ortizbuzarra@estudiante.uam.es>
License: MIT
Requires-Python: >=3.8
License-File: LICENSE
Requires-Dist: torch<2.7,>=2.5.0
Requires-Dist: torchvision<0.21,>=0.20.0
Requires-Dist: numpy<2.2,>=1.24
Requires-Dist: scipy<1.14,>=1.9
Requires-Dist: matplotlib<3.10,>=3.6
Requires-Dist: tqdm<4.68,>=4.64
Requires-Dist: colorlog
Provides-Extra: dev
Requires-Dist: black>=24.4; extra == "dev"
Requires-Dist: ruff>=0.4; extra == "dev"
Dynamic: license-file
